ragmap/__init__.py
ragmap/constants.py
ragmap/ragmap.py
ragmap/utils.py
ragmap-0.1.1.dist-info/LICENSE
ragmap-0.1.1.dist-info/METADATA
ragmap-0.1.1.dist-info/WHEEL
ragmap-0.1.1.dist-info/top_level.txt
ragmap-0.1.1.dist-info/RECORD
