Metadata-Version: 2.1
Name: ragmap
Version: 0.1.1
Summary: RAGmap is a simple RAG visualization package for exploring document chunks and queries in embedding space
Author-email: João Galego <jgalego1990@gmail.com>
License: MIT License
Project-URL: Homepage, https://github.com/JGalego/RAGmap
Keywords: Embeddings,RAG,Visualization
Classifier: License :: OSI Approved :: MIT License
Classifier: Programming Language :: Python
Classifier: Programming Language :: Python :: 3
Classifier: Operating System :: OS Independent
Requires-Python: >=3.8
License-File: LICENSE
Requires-Dist: boto3
Requires-Dist: chromadb
Requires-Dist: langchain
Requires-Dist: numpy
Requires-Dist: opentsne
Requires-Dist: pandas
Requires-Dist: plotly
Requires-Dist: python-docx
Requires-Dist: python-pptx
Requires-Dist: PyPDF2
Requires-Dist: scikit-learn
Requires-Dist: sentence-transformers
Requires-Dist: umap-learn
Provides-Extra: dev
Requires-Dist: black ; extra == 'dev'
Requires-Dist: bumpver ; extra == 'dev'
Requires-Dist: isort ; extra == 'dev'
Requires-Dist: jupyter[notebook] ; extra == 'dev'
Requires-Dist: kaleido ; extra == 'dev'
Requires-Dist: pip-tools ; extra == 'dev'
Requires-Dist: pytest ; extra == 'dev'
